django_upgrade/__init__.py
django_upgrade/__main__.py
django_upgrade/ast.py
django_upgrade/data.py
django_upgrade/main.py
django_upgrade/py.typed
django_upgrade/tokens.py
django_upgrade/fixers/__init__.py
django_upgrade/fixers/admin_allow_tags.py
django_upgrade/fixers/admin_decorators.py
django_upgrade/fixers/admin_lookup_needs_distinct.py
django_upgrade/fixers/admin_register.py
django_upgrade/fixers/assert_form_error.py
django_upgrade/fixers/assert_set_methods.py
django_upgrade/fixers/check_constraint_condition.py
django_upgrade/fixers/compatibility_imports.py
django_upgrade/fixers/crypto_get_random_string.py
django_upgrade/fixers/default_app_config.py
django_upgrade/fixers/default_auto_field.py
django_upgrade/fixers/django_urls.py
django_upgrade/fixers/email_validator.py
django_upgrade/fixers/format_html.py
django_upgrade/fixers/forms_model_multiple_choice_field.py
django_upgrade/fixers/index_together.py
django_upgrade/fixers/mail_api_kwargs.py
django_upgrade/fixers/management_commands.py
django_upgrade/fixers/model_field_choices.py
django_upgrade/fixers/null_boolean_field.py
django_upgrade/fixers/on_delete.py
django_upgrade/fixers/password_reset_timeout_days.py
django_upgrade/fixers/postgres_aggregate_order_by.py
django_upgrade/fixers/postgres_float_range_field.py
django_upgrade/fixers/queryset_paginator.py
django_upgrade/fixers/request_headers.py
django_upgrade/fixers/request_user_attributes.py
django_upgrade/fixers/settings_admins_managers.py
django_upgrade/fixers/settings_database_postgresql.py
django_upgrade/fixers/settings_forms_urlfield_assume_https.py
django_upgrade/fixers/settings_storages.py
django_upgrade/fixers/signal_providing_args.py
django_upgrade/fixers/staticfiles_find_all.py
django_upgrade/fixers/stringagg.py
django_upgrade/fixers/test_http_headers.py
django_upgrade/fixers/testcase_databases.py
django_upgrade/fixers/timezone_fixedoffset.py
django_upgrade/fixers/use_l10n.py
django_upgrade/fixers/utils_encoding.py
django_upgrade-1.29.1.dist-info/licenses/LICENSE
django_upgrade-1.29.1.dist-info/METADATA
django_upgrade-1.29.1.dist-info/WHEEL
django_upgrade-1.29.1.dist-info/entry_points.txt
django_upgrade-1.29.1.dist-info/top_level.txt
django_upgrade-1.29.1.dist-info/RECORD
