Metadata-Version: 2.4
Name: django-upgrade
Version: 1.29.1
Summary: Automatically upgrade your Django project code.
Author-email: Adam Johnson <me@adamj.eu>
License-Expression: MIT
Project-URL: Changelog, https://django-upgrade.readthedocs.io/en/latest/changelog.html
Project-URL: Documentation, https://django-upgrade.readthedocs.io/
Project-URL: Funding, https://adamj.eu/books/
Project-URL: Repository, https://github.com/adamchainz/django-upgrade
Keywords: Django
Classifier: Development Status :: 5 - Production/Stable
Classifier: Framework :: Django :: 2.2
Classifier: Framework :: Django :: 3.0
Classifier: Framework :: Django :: 3.1
Classifier: Framework :: Django :: 3.2
Classifier: Framework :: Django :: 4.0
Classifier: Framework :: Django :: 4.1
Classifier: Framework :: Django :: 4.2
Classifier: Framework :: Django :: 5.0
Classifier: Framework :: Django :: 5.1
Classifier: Framework :: Django :: 5.2
Classifier: Intended Audience :: Developers
Classifier: Natural Language :: English
Classifier: Operating System :: OS Independent
Classifier: Programming Language :: Python :: 3 :: Only
Classifier: Programming Language :: Python :: 3.9
Classifier: Programming Language :: Python :: 3.10
Classifier: Programming Language :: Python :: 3.11
Classifier: Programming Language :: Python :: 3.12
Classifier: Programming Language :: Python :: 3.13
Classifier: Programming Language :: Python :: 3.14
Classifier: Typing :: Typed
Requires-Python: >=3.9
License-File: LICENSE
Requires-Dist: tokenize-rt>=4.1
Dynamic: license-file
